{
    "Version": "2012-10-17",
    "Statement": [
        {
            "Effect": "Allow",
            "Action": [
                "shield:GetSubscriptionState",
                "elasticloadbalancing:DescribeTargetGroups",
                "elasticloadbalancing:DescribeLoadBalancers",
                "elasticloadbalancing:DescribeListeners",
                "elasticloadbalancing:DescribeRules",
                "elasticloadbalancing:DescribeSSLPolicies",
                "elasticloadbalancing:DescribeTags"
            ],
            "Resource": "*"
        }
    ]
}

// aws iam put-role-policy --role-name workers-eks-node-group-20240730140053877100000001 --policy-name EKSWorkerNodePolicy --policy-document file://policy.json
